{
  "investments": [
    {
      "bank": "Post Office",
      "instrument": "Public Provident Fund (PPF)",
      "rate": 7.1
    },
    {
      "bank": "Post Office",
      "instrument": "Sukanya Samriddhi Account (SSA)",
      "rate": 8.2
    },
    {
      "bank": "Post Office",
      "instrument": "Senior Citizen Savings Scheme (SCSS)",
      "rate": 8.2
    },
    {
      "bank": "Post Office",
      "instrument": "Monthly Income Scheme (MIS)",
      "rate": 7.4
    },
    {
      "bank": "Post Office",
      "instrument": "National Savings Certificate (NSC)",
      "rate": 7.7
    },
    {
      "bank": "Post Office",
      "instrument": "Kisan Vikas Patra (KVP)",
      "rate": 7.5
    },
    {
      "bank": "Post Office",
      "instrument": "Time Deposit (TD)",
      "tenures": [
        {"label": "1 Year (6.9%)", "years": 1.0},
        {"label": "2 Years (7.0%)", "years": 2.0},
        {"label": "3 Years (7.1%)", "years": 3.0},
        {"label": "5 Years (7.5%)", "years": 5.0}
      ]
    },
    {
      "bank": "Post Office",
      "instrument": "Recurring Deposit (RD)",
      "rate": 6.7
    },
    {
      "bank": "Post Office",
      "instrument": "Mahila Samman Savings Certificate",
      "rate": 7.5
    },
    {
      "bank": "SBI",
      "instrument": "Fixed Deposit (Regular)",
      "tenures": [
        {"label": "1 Year to <2 Years (6.80%)", "years": 1.0},
        {"label": "2 Years to <3 Years (7.00%)", "years": 2.0},
        {"label": "3 Years to <5 Years (6.75%)", "years": 3.0},
        {"label": "5 Years to 10 Years (6.50%)", "years": 5.0}
      ]
    },
    {
      "bank": "SBI",
      "instrument": "Fixed Deposit (Senior Citizen)",
      "tenures": [
        {"label": "1 Year to <2 Years (7.30%)", "years": 1.0},
        {"label": "2 Years to <3 Years (7.50%)", "years": 2.0},
        {"label": "3 Years to <5 Years (7.25%)", "years": 3.0},
        {"label": "5 Years to 10 Years (7.50%)", "years": 5.0}
      ]
    },
    {
      "bank": "SBI",
      "instrument": "Amrit Kalash Scheme (400 Days)",
      "tenures": [
        {"label": "Regular (7.10%)", "years": 1.09},
        {"label": "Senior Citizen (7.60%)", "years": 1.09}
      ]
    },
    {
      "bank": "PNB",
      "instrument": "Fixed Deposit (Regular)",
      "tenures": [
        {"label": "1 Year (6.75%)", "years": 1.0},
        {"label": "400 Days (7.25%)", "years": 1.09},
        {"label": "2 Years to 3 Years (7.00%)", "years": 2.0},
        {"label": "3 Years to 5 Years (6.50%)", "years": 3.0}
      ]
    },
    {
      "bank": "PNB",
      "instrument": "Fixed Deposit (Senior Citizen)",
      "tenures": [
        {"label": "1 Year (7.25%)", "years": 1.0},
        {"label": "400 Days (7.75%)", "years": 1.09},
        {"label": "2 Years to 3 Years (7.50%)", "years": 2.0},
        {"label": "3 Years to 5 Years (7.00%)", "years": 3.0}
      ]
    },
    {
      "bank": "Bank of Baroda",
      "instrument": "Fixed Deposit (Regular)",
      "tenures": [
        {"label": "1 Year (6.85%)", "years": 1.0},
        {"label": "399 Days - Tiranga Plus (7.15%)", "years": 1.09},
        {"label": "2 Years to 3 Years (7.25%)", "years": 2.0},
        {"label": "3 Years to 5 Years (6.50%)", "years": 3.0}
      ]
    },
    {
      "bank": "Canara Bank",
      "instrument": "Fixed Deposit (Regular)",
      "tenures": [
        {"label": "1 Year (6.85%)", "years": 1.0},
        {"label": "444 Days (7.25%)", "years": 1.21},
        {"label": "2 Years to 3 Years (6.85%)", "years": 2.0},
        {"label": "3 Years to 5 Years (6.80%)", "years": 3.0}
      ]
    }
  ],
  "loans": [
    {
      "bank": "SBI",
      "instrument": "Home Loan (Regular)",
      "rate": 8.50
    },
    {
      "bank": "SBI",
      "instrument": "Home Loan Maxgain (OD)",
      "rate": 8.85
    },
    {
      "bank": "SBI",
      "instrument": "Auto Loan (New Car)",
      "rate": 8.65
    },
    {
      "bank": "SBI",
      "instrument": "Personal Loan",
      "rate": 11.15
    },
    {
      "bank": "SBI",
      "instrument": "Loan Against Property",
      "rate": 10.00
    },
    {
      "bank": "PNB",
      "instrument": "Home Loan (Max Saver)",
      "rate": 8.40
    },
    {
      "bank": "PNB",
      "instrument": "Auto Loan",
      "rate": 8.75
    },
    {
      "bank": "PNB",
      "instrument": "Personal Loan",
      "rate": 10.40
    },
    {
      "bank": "Bank of Baroda",
      "instrument": "Home Loan",
      "rate": 8.40
    },
    {
      "bank": "Bank of Baroda",
      "instrument": "Auto Loan",
      "rate": 8.70
    },
    {
      "bank": "Bank of Baroda",
      "instrument": "Personal Loan",
      "rate": 10.90
    },
    {
      "bank": "Canara Bank",
      "instrument": "Home Loan",
      "rate": 8.40
    },
    {
      "bank": "Canara Bank",
      "instrument": "Auto Loan",
      "rate": 8.70
    },
    {
      "bank": "Canara Bank",
      "instrument": "Personal Loan",
      "rate": 10.95
    }
  ]
}
